py_zhi_01/__init__.py
py_zhi_01/subtraction.py
py_zhi_01-1.0.0.dist-info/LICENSE
py_zhi_01-1.0.0.dist-info/METADATA
py_zhi_01-1.0.0.dist-info/WHEEL
py_zhi_01-1.0.0.dist-info/top_level.txt
py_zhi_01-1.0.0.dist-info/RECORD
