Metadata-Version: 2.1
Name: py-zhi-01
Version: 1.0.0
Summary: reshape data type in py language 
Home-page: http://www.reshapedata.com
Author: zhangzhi
Author-email: 1642699718@qq.com
License: Apache License
Keywords: reshapedata,rdt,pyrdt
Requires-Python: >=3.6
License-File: LICENSE
Requires-Dist: requests
